{"observed_at":"2026-07-20T20:31:00Z","sources":{"point_in_time_token_list":{"added":[],"current_path":"current/token_list.json","record_count":17674,"removed":[],"sha256":"e47fc27399dd01d8c24c95e32570a5cd2af59bba9852a613b01be35df0634d83"},"small_exchange_funding":{"exchange":"gateio","records":[{"funding_next_apply":1784592000,"funding_rate":"0.0001","mark_price":"863.6","name":"CAT_USDT","status":"trading","trade_size":23350},{"funding_next_apply":1784592000,"funding_rate":"0.0001","mark_price":"80.82","name":"BUD_USDT","status":"trading","trade_size":25671},{"funding_next_apply":1784592000,"funding_rate":"0.0001","mark_price":"366.7","name":"MAR_USDT","status":"trading","trade_size":25820},{"funding_next_apply":1784592000,"funding_rate":"0.0001","mark_price":"60.51","name":"BAC_USDT","status":"trading","trade_size":26459},{"funding_next_apply":1784592000,"funding_rate":"0.0001","mark_price":"44.99","name":"XLU_USDT","status":"trading","trade_size":26739},{"funding_next_apply":1784592000,"funding_rate":"0.0001","mark_price":"7.845","name":"WEN_USDT","status":"trading","trade_size":28755},{"funding_next_apply":1784592000,"funding_rate":"0.0001","mark_price":"43.43","name":"NKE_USDT","status":"trading","trade_size":30129},{"funding_next_apply":1784592000,"funding_rate":"0.0001","mark_price":"88.08","name":"NEE_USDT","status":"trading","trade_size":31405},{"funding_next_apply":1784592000,"funding_rate":"0.0001","mark_price":"86.09","name":"PDD_USDT","status":"trading","trade_size":31505},{"funding_next_apply":1784592000,"funding_rate":"0.0001","mark_price":"94.69","name":"SO_USDT","status":"trading","trade_size":31714},{"funding_next_apply":1784592000,"funding_rate":"0.0001","mark_price":"62.79","name":"AMKR_USDT","status":"trading","trade_size":33084},{"funding_next_apply":1784592000,"funding_rate":"0.0001","mark_price":"310.08","name":"NEURALINK_USDT","status":"trading","trade_size":33141},{"funding_next_apply":1784592000,"funding_rate":"0.0001","mark_price":"86.68","name":"WFC_USDT","status":"trading","trade_size":35093},{"funding_next_apply":1784592000,"funding_rate":"0.0001","mark_price":"102.9","name":"SCHW_USDT","status":"trading","trade_size":35519},{"funding_next_apply":1784592000,"funding_rate":"0.0001","mark_price":"107.51","name":"CVS_USDT","status":"trading","trade_size":38818},{"funding_next_apply":1784592000,"funding_rate":"0.0001","mark_price":"151.4","name":"XBI_USDT","status":"trading","trade_size":39330},{"funding_next_apply":1784592000,"funding_rate":"0.0001","mark_price":"57.39","name":"FOXA_USDT","status":"trading","trade_size":39884},{"funding_next_apply":1784592000,"funding_rate":"0.0001","mark_price":"44.01","name":"BSX_USDT","status":"trading","trade_size":42560},{"funding_next_apply":1784592000,"funding_rate":"0.0001","mark_price":"239.9","name":"TTWO_USDT","status":"trading","trade_size":42981},{"funding_next_apply":1784592000,"funding_rate":"0.0001","mark_price":"80.93","name":"MCHP_USDT","status":"trading","trade_size":47624},{"funding_next_apply":1784592000,"funding_rate":"0.0001","mark_price":"490.2","name":"SPOT_USDT","status":"trading","trade_size":48829},{"funding_next_apply":1784592000,"funding_rate":"0.0001","mark_price":"528.7","name":"TMO_USDT","status":"trading","trade_size":48969},{"funding_next_apply":1784592000,"funding_rate":"0.0001","mark_price":"15.131","name":"AAL_USDT","status":"trading","trade_size":49600},{"funding_next_apply":1784592000,"funding_rate":"0.0001","mark_price":"56.06","name":"XLF_USDT","status":"trading","trade_size":52393},{"funding_next_apply":1784592000,"funding_rate":"0.0001","mark_price":"63.65","name":"EEM_USDT","status":"trading","trade_size":54184},{"funding_next_apply":1784592000,"funding_rate":"0.0001","mark_price":"87.34","name":"STRC_USDT","status":"trading","trade_size":55512},{"funding_next_apply":1784592000,"funding_rate":"0.0001","mark_price":"26.056","name":"CCL_USDT","status":"trading","trade_size":56427},{"funding_next_apply":1784592000,"funding_rate":"0.0001","mark_price":"513.4","name":"LIN_USDT","status":"trading","trade_size":56688},{"funding_next_apply":1784592000,"funding_rate":"0.0001","mark_price":"364.2","name":"AMGN_USDT","status":"trading","trade_size":58621},{"funding_next_apply":1784592000,"funding_rate":"0.0001","mark_price":"292.82","name":"INTU_USDT","status":"trading","trade_size":58660},{"funding_next_apply":1784592000,"funding_rate":"0.0001","mark_price":"58.92","name":"FCX_USDT","status":"trading","trade_size":59143},{"funding_next_apply":1784592000,"funding_rate":"0.0001","mark_price":"23.844","name":"CMCSA_USDT","status":"trading","trade_size":60606},{"funding_next_apply":1784592000,"funding_rate":"0.0001","mark_price":"36.91","name":"ASX_USDT","status":"trading","trade_size":62346},{"funding_next_apply":1784592000,"funding_rate":"0.0001","mark_price":"195.03","name":"TMUS_USDT","status":"trading","trade_size":62943},{"funding_next_apply":1784592000,"funding_rate":"0.0001","mark_price":"24.789","name":"PFE_USDT","status":"trading","trade_size":63824},{"funding_next_apply":1784592000,"funding_rate":"0.0001","mark_price":"322.2","name":"SYK_USDT","status":"trading","trade_size":66337},{"funding_next_apply":1784592000,"funding_rate":"0.0001","mark_price":"1831.9","name":"MELI_USDT","status":"trading","trade_size":67144},{"funding_next_apply":1784592000,"funding_rate":"0.0001","mark_price":"155.85","name":"TJX_USDT","status":"trading","trade_size":67199},{"funding_next_apply":1784592000,"funding_rate":"0.0001","mark_price":"144.55","name":"ABNB_USDT","status":"trading","trade_size":70012},{"funding_next_apply":1784592000,"funding_rate":"0.0001","mark_price":"206.2","name":"COF_USDT","status":"trading","trade_size":70278},{"funding_next_apply":1784592000,"funding_rate":"0.0001","mark_price":"1076.9","name":"GEV_USDT","status":"trading","trade_size":71194},{"funding_next_apply":1784592000,"funding_rate":"0.0001","mark_price":"459.7","name":"ROK_USDT","status":"trading","trade_size":71345},{"funding_next_apply":1784592000,"funding_rate":"0.0001","mark_price":"297.35","name":"APD_USDT","status":"trading","trade_size":75022},{"funding_next_apply":1784592000,"funding_rate":"0.0001","mark_price":"63.18","name":"CGNX_USDT","status":"trading","trade_size":75619},{"funding_next_apply":1784592000,"funding_rate":"0.0001","mark_price":"115.21","name":"COP_USDT","status":"trading","trade_size":75899},{"funding_next_apply":1784592000,"funding_rate":"0.0001","mark_price":"372.4","name":"ADI_USDT","status":"trading","trade_size":76231},{"funding_next_apply":1784592000,"funding_rate":"0.0001","mark_price":"62.01","name":"STM_USDT","status":"trading","trade_size":76524},{"funding_next_apply":1784592000,"funding_rate":"0.0001","mark_price":"175.89","name":"XLK_USDT","status":"trading","trade_size":77406},{"funding_next_apply":1784592000,"funding_rate":"0.0001","mark_price":"367.9","name":"GLD_USDT","status":"trading","trade_size":87112},{"funding_next_apply":1784592000,"funding_rate":"0.0001","mark_price":"87.36","name":"SPYM_USDT","status":"trading","trade_size":89540},{"funding_next_apply":1784592000,"funding_rate":"0.0001","mark_price":"179.49","name":"BKNG_USDT","status":"trading","trade_size":90236},{"funding_next_apply":1784592000,"funding_rate":"0.0001","mark_price":"107.05","name":"LQD_USDT","status":"trading","trade_size":92476},{"funding_next_apply":1784592000,"funding_rate":"0.0001","mark_price":"1702.5","name":"FIX_USDT","status":"trading","trade_size":93529},{"funding_next_apply":1784592000,"funding_rate":"0.0001","mark_price":"354","name":"ISRG_USDT","status":"trading","trade_size":93800},{"funding_next_apply":1784592000,"funding_rate":"0.0001","mark_price":"21.204","name":"SONY_USDT","status":"trading","trade_size":101087},{"funding_next_apply":1784592000,"funding_rate":"0.0001","mark_price":"349.27","name":"PANW_USDT","status":"trading","trade_size":102407},{"funding_next_apply":1784592000,"funding_rate":"0.0001","mark_price":"144.2","name":"ROKU_USDT","status":"trading","trade_size":108353},{"funding_next_apply":1784592000,"funding_rate":"0.0001","mark_price":"1055","name":"GS_USDT","status":"trading","trade_size":120718},{"funding_next_apply":1784592000,"funding_rate":"0.0001","mark_price":"36.91","name":"IBIT_USDT","status":"trading","trade_size":124318},{"funding_next_apply":1784592000,"funding_rate":"0.0001","mark_price":"43.52","name":"VZ_USDT","status":"trading","trade_size":132860},{"funding_next_apply":1784592000,"funding_rate":"0.0001","mark_price":"124.98","name":"MRK_USDT","status":"trading","trade_size":150672},{"funding_next_apply":1784592000,"funding_rate":"0.0001","mark_price":"124.86","name":"SHOP_USDT","status":"trading","trade_size":158860},{"funding_next_apply":1784592000,"funding_rate":"0.0001","mark_price":"35.51","name":"EWZ_USDT","status":"trading","trade_size":168712},{"funding_next_apply":1784592000,"funding_rate":"0.0001","mark_price":"70.74","name":"GDX_USDT","status":"trading","trade_size":176269},{"funding_next_apply":1784592000,"funding_rate":"0.0001","mark_price":"378.3","name":"CIEN_USDT","status":"trading","trade_size":191330},{"funding_next_apply":1784592000,"funding_rate":"0.0001","mark_price":"60.29","name":"SHLD_USDT","status":"trading","trade_size":194365},{"funding_next_apply":1784592000,"funding_rate":"0.0001","mark_price":"205.68","name":"TWLO_USDT","status":"trading","trade_size":197351},{"funding_next_apply":1784592000,"funding_rate":"0.0001","mark_price":"557.6","name":"SMH_USDT","status":"trading","trade_size":204461},{"funding_next_apply":1784592000,"funding_rate":"0.0001","mark_price":"120.12","name":"FLEX_USDT","status":"trading","trade_size":213463},{"funding_next_apply":1784592000,"funding_rate":"0.0001","mark_price":"424.2","name":"APP_USDT","status":"trading","trade_size":214234},{"funding_next_apply":1784592000,"funding_rate":"0.0001","mark_price":"67.08","name":"CARR_USDT","status":"trading","trade_size":215718},{"funding_next_apply":1784592000,"funding_rate":"0.0001","mark_price":"114.32","name":"EBAY_USDT","status":"trading","trade_size":227394},{"funding_next_apply":1784592000,"funding_rate":"0.0001","mark_price":"740.3","name":"IVV_USDT","status":"trading","trade_size":231904},{"funding_next_apply":1784592000,"funding_rate":"0.0001","mark_price":"640","name":"CMI_USDT","status":"trading","trade_size":233283},{"funding_next_apply":1784592000,"funding_rate":"0.0001","mark_price":"58.05","name":"XLE_USDT","status":"trading","trade_size":234851},{"funding_next_apply":1784592000,"funding_rate":"0.0001","mark_price":"48.27","name":"URNM_USDT","status":"trading","trade_size":240936},{"funding_next_apply":1784592000,"funding_rate":"0.0001","mark_price":"680.4","name":"VOO_USDT","status":"trading","trade_size":264372},{"funding_next_apply":1784592000,"funding_rate":"0.0001","mark_price":"21.764","name":"GME_USDT","status":"trading","trade_size":264465},{"funding_next_apply":1784592000,"funding_rate":"0.0001","mark_price":"322.4","name":"MDB_USDT","status":"trading","trade_size":267546},{"funding_next_apply":1784592000,"funding_rate":"0.0001","mark_price":"307.9","name":"CLS_USDT","status":"trading","trade_size":269901},{"funding_next_apply":1784592000,"funding_rate":"0.0001","mark_price":"473.3","name":"FN_USDT","status":"trading","trade_size":279722},{"funding_next_apply":1784592000,"funding_rate":"0.0001","mark_price":"1331.1","name":"MPWR_USDT","status":"trading","trade_size":281969},{"funding_next_apply":1784592000,"funding_rate":"0.0001","mark_price":"332.9","name":"HD_USDT","status":"trading","trade_size":290519},{"funding_next_apply":1784592000,"funding_rate":"0.0001","mark_price":"249.53","name":"JNJ_USDT","status":"trading","trade_size":315286},{"funding_next_apply":1784592000,"funding_rate":"0.0001","mark_price":"333.2","name":"TER_USDT","status":"trading","trade_size":319849},{"funding_next_apply":1784592000,"funding_rate":"0.0001","mark_price":"72.25","name":"UBER_USDT","status":"trading","trade_size":320186},{"funding_next_apply":1784592000,"funding_rate":"0.0001","mark_price":"169.77","name":"ANET_USDT","status":"trading","trade_size":320869},{"funding_next_apply":1784592000,"funding_rate":"0.0001","mark_price":"151.39","name":"APH_USDT","status":"trading","trade_size":326801},{"funding_next_apply":1784592000,"funding_rate":"0.0001","mark_price":"49.86","name":"NVO_USDT","status":"trading","trade_size":339049},{"funding_next_apply":1784592000,"funding_rate":"0.0001","mark_price":"2.397","name":"GEELY_USDT","status":"trading","trade_size":339512},{"funding_next_apply":1784592000,"funding_rate":"0.0001","mark_price":"3.386","name":"TRAHK_USDT","status":"trading","trade_size":347307},{"funding_next_apply":1784592000,"funding_rate":"0.0001","mark_price":"34.36","name":"IONQ_USDT","status":"trading","trade_size":347329},{"funding_next_apply":1784592000,"funding_rate":"0.0001","mark_price":"253.3","name":"CEG_USDT","status":"trading","trade_size":356805},{"funding_next_apply":1784592000,"funding_rate":"0.0001","mark_price":"42.71","name":"SQQQ_USDT","status":"trading","trade_size":357183},{"funding_next_apply":1784592000,"funding_rate":"0.0001","mark_price":"4.58","name":"DEEPTECH_USDT","status":"trading","trade_size":359655},{"funding_next_apply":1784592000,"funding_rate":"0.0001","mark_price":"21.033","name":"POPMART_USDT","status":"trading","trade_size":371035},{"funding_next_apply":1784592000,"funding_rate":"0.0001","mark_price":"205.58","name":"FSLR_USDT","status":"trading","trade_size":372200},{"funding_next_apply":1784592000,"funding_rate":"0.0001","mark_price":"170.9","name":"BWXT_USDT","status":"trading","trade_size":379231},{"funding_next_apply":1784592000,"funding_rate":"0.0001","mark_price":"360.7","name":"V_USDT","status":"trading","trade_size":380288},{"funding_next_apply":1784592000,"funding_rate":"0.0001","mark_price":"139.41","name":"JCI_USDT","status":"trading","trade_size":397615}],"selection":"100_lowest_positive_trade_size","sha256":"36d82004c7d3488a374a0a8ba616e1aba8f3043984de75fa0a66be42042bfbaa"},"thin_orderbook":{"asks":[{"p":"865.5","s":1},{"p":"866.8","s":8},{"p":"868.1","s":72},{"p":"869.4","s":42},{"p":"870.2","s":72},{"p":"870.8","s":47},{"p":"870.9","s":51},{"p":"871","s":54},{"p":"871.1","s":58},{"p":"871.2","s":52},{"p":"871.3","s":50},{"p":"871.4","s":50},{"p":"871.5","s":59},{"p":"871.6","s":37},{"p":"871.7","s":49},{"p":"871.8","s":48},{"p":"871.9","s":62},{"p":"872","s":65},{"p":"872.1","s":46},{"p":"872.2","s":64},{"p":"872.3","s":56},{"p":"872.4","s":61},{"p":"872.5","s":51},{"p":"872.6","s":48},{"p":"872.7","s":47},{"p":"872.8","s":49},{"p":"872.9","s":49},{"p":"873","s":61},{"p":"873.1","s":50},{"p":"873.2","s":37},{"p":"881","s":46},{"p":"881.1","s":53},{"p":"881.2","s":53},{"p":"881.3","s":40},{"p":"881.4","s":40},{"p":"881.5","s":49},{"p":"881.6","s":48},{"p":"881.7","s":39},{"p":"881.8","s":40},{"p":"881.9","s":43},{"p":"882","s":43},{"p":"882.1","s":54},{"p":"882.2","s":48},{"p":"882.3","s":51},{"p":"882.4","s":51},{"p":"882.5","s":39},{"p":"882.6","s":37},{"p":"882.7","s":38},{"p":"882.8","s":51},{"p":"882.9","s":38}],"bids":[{"p":"861.9","s":41},{"p":"860.5","s":1},{"p":"857.9","s":40},{"p":"857.5","s":38},{"p":"856.6","s":59},{"p":"856.5","s":62},{"p":"856.4","s":43},{"p":"856.3","s":59},{"p":"856.2","s":49},{"p":"856.1","s":47},{"p":"856","s":69},{"p":"855.9","s":52},{"p":"855.8","s":62},{"p":"855.7","s":50},{"p":"855.6","s":60},{"p":"855.5","s":68},{"p":"855.4","s":43},{"p":"855.3","s":49},{"p":"855.2","s":53},{"p":"855.1","s":57},{"p":"855","s":69},{"p":"854.9","s":48},{"p":"854.8","s":47},{"p":"854.7","s":62},{"p":"854.6","s":59},{"p":"854.5","s":55},{"p":"854.4","s":67},{"p":"854.3","s":68},{"p":"854.2","s":54},{"p":"846.4","s":52},{"p":"846.3","s":43},{"p":"846.2","s":56},{"p":"846.1","s":55},{"p":"846","s":44},{"p":"845.9","s":50},{"p":"845.8","s":40},{"p":"845.7","s":42},{"p":"845.6","s":44},{"p":"845.5","s":54},{"p":"845.4","s":40},{"p":"845.3","s":45},{"p":"845.2","s":50},{"p":"845.1","s":50},{"p":"845","s":47},{"p":"844.9","s":54},{"p":"844.8","s":56},{"p":"844.7","s":595},{"p":"844.6","s":41},{"p":"844.5","s":56},{"p":"844.4","s":56}],"contract":"CAT_USDT","exchange":"gateio","selection":"lowest_positive_trade_size","sha256":"479528000dfc73489b830c10da8977f0479ae6edb9428ebd791035d3e79afe08"}}}
