{"observed_at":"2026-07-20T21:01:00Z","sources":{"point_in_time_token_list":{"added":[],"current_path":"current/token_list.json","record_count":17674,"removed":[],"sha256":"e47fc27399dd01d8c24c95e32570a5cd2af59bba9852a613b01be35df0634d83"},"small_exchange_funding":{"exchange":"gateio","records":[{"funding_next_apply":1784592000,"funding_rate":"0.0001","mark_price":"864.3","name":"CAT_USDT","status":"trading","trade_size":23356},{"funding_next_apply":1784592000,"funding_rate":"0.0001","mark_price":"80.84","name":"BUD_USDT","status":"trading","trade_size":25678},{"funding_next_apply":1784592000,"funding_rate":"0.0001","mark_price":"366.7","name":"MAR_USDT","status":"trading","trade_size":25843},{"funding_next_apply":1784592000,"funding_rate":"0.0001","mark_price":"60.43","name":"BAC_USDT","status":"trading","trade_size":26468},{"funding_next_apply":1784592000,"funding_rate":"0.0001","mark_price":"44.99","name":"XLU_USDT","status":"trading","trade_size":26760},{"funding_next_apply":1784592000,"funding_rate":"0.0001","mark_price":"7.846","name":"WEN_USDT","status":"trading","trade_size":28761},{"funding_next_apply":1784592000,"funding_rate":"0.0001","mark_price":"43.42","name":"NKE_USDT","status":"trading","trade_size":30150},{"funding_next_apply":1784592000,"funding_rate":"0.0001","mark_price":"88.06","name":"NEE_USDT","status":"trading","trade_size":31409},{"funding_next_apply":1784592000,"funding_rate":"0.0001","mark_price":"85.92","name":"PDD_USDT","status":"trading","trade_size":31533},{"funding_next_apply":1784592000,"funding_rate":"0.0001","mark_price":"94.69","name":"SO_USDT","status":"trading","trade_size":31716},{"funding_next_apply":1784592000,"funding_rate":"0.0001","mark_price":"62.9","name":"AMKR_USDT","status":"trading","trade_size":33093},{"funding_next_apply":1784592000,"funding_rate":"0.0001","mark_price":"310.08","name":"NEURALINK_USDT","status":"trading","trade_size":33141},{"funding_next_apply":1784592000,"funding_rate":"0.0001","mark_price":"86.34","name":"WFC_USDT","status":"trading","trade_size":35097},{"funding_next_apply":1784592000,"funding_rate":"0.0001","mark_price":"102.79","name":"SCHW_USDT","status":"trading","trade_size":35541},{"funding_next_apply":1784592000,"funding_rate":"0.0001","mark_price":"107.5","name":"CVS_USDT","status":"trading","trade_size":38820},{"funding_next_apply":1784592000,"funding_rate":"0.0001","mark_price":"151.45","name":"XBI_USDT","status":"trading","trade_size":39360},{"funding_next_apply":1784592000,"funding_rate":"0.0001","mark_price":"57.32","name":"FOXA_USDT","status":"trading","trade_size":39899},{"funding_next_apply":1784592000,"funding_rate":"0.0001","mark_price":"43.98","name":"BSX_USDT","status":"trading","trade_size":42577},{"funding_next_apply":1784592000,"funding_rate":"0.0001","mark_price":"239.6","name":"TTWO_USDT","status":"trading","trade_size":43009},{"funding_next_apply":1784592000,"funding_rate":"0.0001","mark_price":"80.61","name":"MCHP_USDT","status":"trading","trade_size":47648},{"funding_next_apply":1784592000,"funding_rate":"0.0001","mark_price":"490.1","name":"SPOT_USDT","status":"trading","trade_size":48848},{"funding_next_apply":1784592000,"funding_rate":"0.0001","mark_price":"528.8","name":"TMO_USDT","status":"trading","trade_size":48986},{"funding_next_apply":1784592000,"funding_rate":"0.0001","mark_price":"15.16","name":"AAL_USDT","status":"trading","trade_size":49630},{"funding_next_apply":1784592000,"funding_rate":"0.0001","mark_price":"56.05","name":"XLF_USDT","status":"trading","trade_size":52405},{"funding_next_apply":1784592000,"funding_rate":"0.0001","mark_price":"63.65","name":"EEM_USDT","status":"trading","trade_size":54193},{"funding_next_apply":1784592000,"funding_rate":"0.0001","mark_price":"87.52","name":"STRC_USDT","status":"trading","trade_size":55601},{"funding_next_apply":1784592000,"funding_rate":"0.0001","mark_price":"26.049","name":"CCL_USDT","status":"trading","trade_size":56453},{"funding_next_apply":1784592000,"funding_rate":"0.0001","mark_price":"513.3","name":"LIN_USDT","status":"trading","trade_size":56704},{"funding_next_apply":1784592000,"funding_rate":"0.0001","mark_price":"364.2","name":"AMGN_USDT","status":"trading","trade_size":58644},{"funding_next_apply":1784592000,"funding_rate":"0.0001","mark_price":"293.41","name":"INTU_USDT","status":"trading","trade_size":58686},{"funding_next_apply":1784592000,"funding_rate":"0.0001","mark_price":"58.92","name":"FCX_USDT","status":"trading","trade_size":59155},{"funding_next_apply":1784592000,"funding_rate":"0.0001","mark_price":"23.843","name":"CMCSA_USDT","status":"trading","trade_size":60632},{"funding_next_apply":1784592000,"funding_rate":"0.0001","mark_price":"36.87","name":"ASX_USDT","status":"trading","trade_size":62370},{"funding_next_apply":1784592000,"funding_rate":"0.0001","mark_price":"194.6","name":"TMUS_USDT","status":"trading","trade_size":62972},{"funding_next_apply":1784592000,"funding_rate":"0.0001","mark_price":"24.794","name":"PFE_USDT","status":"trading","trade_size":63852},{"funding_next_apply":1784592000,"funding_rate":"0.0001","mark_price":"321","name":"SYK_USDT","status":"trading","trade_size":66363},{"funding_next_apply":1784592000,"funding_rate":"0.0001","mark_price":"1832.5","name":"MELI_USDT","status":"trading","trade_size":67173},{"funding_next_apply":1784592000,"funding_rate":"0.0001","mark_price":"155.85","name":"TJX_USDT","status":"trading","trade_size":67229},{"funding_next_apply":1784592000,"funding_rate":"0.0001","mark_price":"144.64","name":"ABNB_USDT","status":"trading","trade_size":70042},{"funding_next_apply":1784592000,"funding_rate":"0.0001","mark_price":"206.21","name":"COF_USDT","status":"trading","trade_size":70307},{"funding_next_apply":1784592000,"funding_rate":"0.0001","mark_price":"1078","name":"GEV_USDT","status":"trading","trade_size":71224},{"funding_next_apply":1784592000,"funding_rate":"0.0001","mark_price":"458.8","name":"ROK_USDT","status":"trading","trade_size":71363},{"funding_next_apply":1784592000,"funding_rate":"0.0001","mark_price":"296.95","name":"APD_USDT","status":"trading","trade_size":75047},{"funding_next_apply":1784592000,"funding_rate":"0.0001","mark_price":"63.07","name":"CGNX_USDT","status":"trading","trade_size":75631},{"funding_next_apply":1784592000,"funding_rate":"0.0001","mark_price":"115.3","name":"COP_USDT","status":"trading","trade_size":75931},{"funding_next_apply":1784592000,"funding_rate":"0.0001","mark_price":"372.2","name":"ADI_USDT","status":"trading","trade_size":76331},{"funding_next_apply":1784592000,"funding_rate":"0.0001","mark_price":"61.97","name":"STM_USDT","status":"trading","trade_size":76565},{"funding_next_apply":1784592000,"funding_rate":"0.0001","mark_price":"175.89","name":"XLK_USDT","status":"trading","trade_size":77435},{"funding_next_apply":1784592000,"funding_rate":"0.0001","mark_price":"367.9","name":"GLD_USDT","status":"trading","trade_size":87137},{"funding_next_apply":1784592000,"funding_rate":"0.0001","mark_price":"87.36","name":"SPYM_USDT","status":"trading","trade_size":89565},{"funding_next_apply":1784592000,"funding_rate":"0.0001","mark_price":"179.44","name":"BKNG_USDT","status":"trading","trade_size":90266},{"funding_next_apply":1784592000,"funding_rate":"0.0001","mark_price":"107.06","name":"LQD_USDT","status":"trading","trade_size":92508},{"funding_next_apply":1784592000,"funding_rate":"0.0001","mark_price":"1702.4","name":"FIX_USDT","status":"trading","trade_size":93558},{"funding_next_apply":1784592000,"funding_rate":"0.0001","mark_price":"353.8","name":"ISRG_USDT","status":"trading","trade_size":93824},{"funding_next_apply":1784592000,"funding_rate":"0.0001","mark_price":"21.202","name":"SONY_USDT","status":"trading","trade_size":101117},{"funding_next_apply":1784592000,"funding_rate":"0.0001","mark_price":"349.12","name":"PANW_USDT","status":"trading","trade_size":102430},{"funding_next_apply":1784592000,"funding_rate":"0.0001","mark_price":"144.15","name":"ROKU_USDT","status":"trading","trade_size":108383},{"funding_next_apply":1784592000,"funding_rate":"0.0001","mark_price":"1057.7","name":"GS_USDT","status":"trading","trade_size":120751},{"funding_next_apply":1784592000,"funding_rate":"0.0001","mark_price":"36.92","name":"IBIT_USDT","status":"trading","trade_size":124342},{"funding_next_apply":1784592000,"funding_rate":"0.0001","mark_price":"43.54","name":"VZ_USDT","status":"trading","trade_size":132878},{"funding_next_apply":1784592000,"funding_rate":"0.0001","mark_price":"124.91","name":"MRK_USDT","status":"trading","trade_size":150703},{"funding_next_apply":1784592000,"funding_rate":"0.0001","mark_price":"124.84","name":"SHOP_USDT","status":"trading","trade_size":158892},{"funding_next_apply":1784592000,"funding_rate":"0.0001","mark_price":"35.57","name":"EWZ_USDT","status":"trading","trade_size":168736},{"funding_next_apply":1784592000,"funding_rate":"0.0001","mark_price":"71.08","name":"GDX_USDT","status":"trading","trade_size":176410},{"funding_next_apply":1784592000,"funding_rate":"0.0001","mark_price":"378.1","name":"CIEN_USDT","status":"trading","trade_size":191354},{"funding_next_apply":1784592000,"funding_rate":"0.0001","mark_price":"60.29","name":"SHLD_USDT","status":"trading","trade_size":194379},{"funding_next_apply":1784592000,"funding_rate":"0.0001","mark_price":"205.16","name":"TWLO_USDT","status":"trading","trade_size":197379},{"funding_next_apply":1784592000,"funding_rate":"0.0001","mark_price":"556.3","name":"SMH_USDT","status":"trading","trade_size":204475},{"funding_next_apply":1784592000,"funding_rate":"0.0001","mark_price":"119.99","name":"FLEX_USDT","status":"trading","trade_size":213494},{"funding_next_apply":1784592000,"funding_rate":"0.0001","mark_price":"424.5","name":"APP_USDT","status":"trading","trade_size":214455},{"funding_next_apply":1784592000,"funding_rate":"0.0001","mark_price":"67.13","name":"CARR_USDT","status":"trading","trade_size":215727},{"funding_next_apply":1784592000,"funding_rate":"0.0001","mark_price":"114.32","name":"EBAY_USDT","status":"trading","trade_size":227426},{"funding_next_apply":1784592000,"funding_rate":"0.0001","mark_price":"740.2","name":"IVV_USDT","status":"trading","trade_size":231984},{"funding_next_apply":1784592000,"funding_rate":"0.0001","mark_price":"641","name":"CMI_USDT","status":"trading","trade_size":233294},{"funding_next_apply":1784592000,"funding_rate":"0.0001","mark_price":"58.04","name":"XLE_USDT","status":"trading","trade_size":234862},{"funding_next_apply":1784592000,"funding_rate":"0.0001","mark_price":"48.31","name":"URNM_USDT","status":"trading","trade_size":240951},{"funding_next_apply":1784592000,"funding_rate":"0.0001","mark_price":"680.4","name":"VOO_USDT","status":"trading","trade_size":264382},{"funding_next_apply":1784592000,"funding_rate":"0.0001","mark_price":"21.75","name":"GME_USDT","status":"trading","trade_size":264507},{"funding_next_apply":1784592000,"funding_rate":"0.0001","mark_price":"324.7","name":"MDB_USDT","status":"trading","trade_size":267570},{"funding_next_apply":1784592000,"funding_rate":"0.0001","mark_price":"306.9","name":"CLS_USDT","status":"trading","trade_size":269926},{"funding_next_apply":1784592000,"funding_rate":"0.0001","mark_price":"487.6","name":"FN_USDT","status":"trading","trade_size":279784},{"funding_next_apply":1784592000,"funding_rate":"0.0001","mark_price":"1330.1","name":"MPWR_USDT","status":"trading","trade_size":281999},{"funding_next_apply":1784592000,"funding_rate":"0.0001","mark_price":"332.8","name":"HD_USDT","status":"trading","trade_size":290544},{"funding_next_apply":1784592000,"funding_rate":"0.0001","mark_price":"249.49","name":"JNJ_USDT","status":"trading","trade_size":315312},{"funding_next_apply":1784592000,"funding_rate":"0.0001","mark_price":"334","name":"TER_USDT","status":"trading","trade_size":319977},{"funding_next_apply":1784592000,"funding_rate":"0.0001","mark_price":"72.12","name":"UBER_USDT","status":"trading","trade_size":320263},{"funding_next_apply":1784592000,"funding_rate":"0.0001","mark_price":"169.75","name":"ANET_USDT","status":"trading","trade_size":320899},{"funding_next_apply":1784592000,"funding_rate":"0.0001","mark_price":"151.39","name":"APH_USDT","status":"trading","trade_size":326831},{"funding_next_apply":1784592000,"funding_rate":"0.0001","mark_price":"49.95","name":"NVO_USDT","status":"trading","trade_size":339071},{"funding_next_apply":1784592000,"funding_rate":"0.0001","mark_price":"2.396","name":"GEELY_USDT","status":"trading","trade_size":339538},{"funding_next_apply":1784592000,"funding_rate":"0.0001","mark_price":"3.386","name":"TRAHK_USDT","status":"trading","trade_size":347331},{"funding_next_apply":1784592000,"funding_rate":"0.0001","mark_price":"34.35","name":"IONQ_USDT","status":"trading","trade_size":347482},{"funding_next_apply":1784592000,"funding_rate":"0.0001","mark_price":"253","name":"CEG_USDT","status":"trading","trade_size":356839},{"funding_next_apply":1784592000,"funding_rate":"0.0001","mark_price":"42.6","name":"SQQQ_USDT","status":"trading","trade_size":357502},{"funding_next_apply":1784592000,"funding_rate":"0.0001","mark_price":"4.579","name":"DEEPTECH_USDT","status":"trading","trade_size":359672},{"funding_next_apply":1784592000,"funding_rate":"0.0001","mark_price":"21.033","name":"POPMART_USDT","status":"trading","trade_size":371062},{"funding_next_apply":1784592000,"funding_rate":"0.0001","mark_price":"205.82","name":"FSLR_USDT","status":"trading","trade_size":372228},{"funding_next_apply":1784592000,"funding_rate":"0.0001","mark_price":"170.9","name":"BWXT_USDT","status":"trading","trade_size":379261},{"funding_next_apply":1784592000,"funding_rate":"0.0001","mark_price":"360.9","name":"V_USDT","status":"trading","trade_size":380320},{"funding_next_apply":1784592000,"funding_rate":"0.0001","mark_price":"139.66","name":"JCI_USDT","status":"trading","trade_size":397646}],"selection":"100_lowest_positive_trade_size","sha256":"887509623bbb25e304a117d251d40e53a989b570de230e580df41f9fa6d9a6cf"},"thin_orderbook":{"asks":[{"p":"866.6","s":1},{"p":"867.9","s":8},{"p":"868.1","s":72},{"p":"869.4","s":42},{"p":"870.2","s":72},{"p":"871.4","s":65},{"p":"871.5","s":59},{"p":"871.6","s":37},{"p":"871.7","s":49},{"p":"871.8","s":48},{"p":"871.9","s":62},{"p":"872","s":65},{"p":"872.1","s":46},{"p":"872.2","s":64},{"p":"872.3","s":56},{"p":"872.4","s":61},{"p":"872.5","s":51},{"p":"872.6","s":48},{"p":"872.7","s":47},{"p":"872.8","s":49},{"p":"872.9","s":65},{"p":"873","s":67},{"p":"873.1","s":62},{"p":"873.2","s":60},{"p":"873.3","s":62},{"p":"873.4","s":48},{"p":"873.5","s":59},{"p":"873.6","s":37},{"p":"873.7","s":52},{"p":"873.8","s":60},{"p":"881.6","s":49},{"p":"881.7","s":39},{"p":"881.8","s":40},{"p":"881.9","s":43},{"p":"882","s":43},{"p":"882.1","s":54},{"p":"882.2","s":48},{"p":"882.3","s":51},{"p":"882.4","s":51},{"p":"882.5","s":566},{"p":"882.6","s":37},{"p":"882.7","s":38},{"p":"882.8","s":51},{"p":"882.9","s":38},{"p":"883","s":38},{"p":"883.1","s":52},{"p":"883.2","s":42},{"p":"883.3","s":44},{"p":"883.4","s":48},{"p":"883.5","s":42}],"bids":[{"p":"861.9","s":41},{"p":"860.5","s":1},{"p":"857.9","s":40},{"p":"857.5","s":38},{"p":"857.2","s":25},{"p":"857.1","s":69},{"p":"857","s":68},{"p":"856.9","s":65},{"p":"856.8","s":60},{"p":"856.7","s":63},{"p":"856.6","s":59},{"p":"856.5","s":57},{"p":"856.4","s":56},{"p":"856.3","s":50},{"p":"856.2","s":49},{"p":"856.1","s":47},{"p":"856","s":69},{"p":"855.9","s":52},{"p":"855.8","s":62},{"p":"855.7","s":50},{"p":"855.6","s":60},{"p":"855.5","s":68},{"p":"855.4","s":43},{"p":"855.3","s":49},{"p":"855.2","s":53},{"p":"855.1","s":57},{"p":"855","s":69},{"p":"854.9","s":48},{"p":"854.8","s":55},{"p":"847","s":42},{"p":"846.9","s":50},{"p":"846.8","s":51},{"p":"846.7","s":45},{"p":"846.6","s":45},{"p":"846.5","s":49},{"p":"846.4","s":51},{"p":"846.3","s":42},{"p":"846.2","s":40},{"p":"846.1","s":47},{"p":"846","s":44},{"p":"845.9","s":50},{"p":"845.8","s":40},{"p":"845.7","s":42},{"p":"845.6","s":44},{"p":"845.5","s":54},{"p":"845.4","s":579},{"p":"845.3","s":45},{"p":"845.2","s":50},{"p":"845.1","s":50},{"p":"845","s":47}],"contract":"CAT_USDT","exchange":"gateio","selection":"lowest_positive_trade_size","sha256":"afb5dea428673cf540973f626295d048a769e96838278ed59b5f79ba65c4940f"}}}
