{"observed_at":"2026-07-17T14:30:00Z","sources":{"point_in_time_token_list":{"added":[],"current_path":"current/token_list.json","record_count":17630,"removed":[],"sha256":"bbdce66c43f9d19b237fe36c89ecfda5cf760fe895ca406d1f2ed9ef2a510b79"},"small_exchange_funding":{"exchange":"gateio","records":[{"funding_next_apply":1784304000,"funding_rate":"0.0001","mark_price":"875.5","name":"CAT_USDT","status":"trading","trade_size":17650},{"funding_next_apply":1784304000,"funding_rate":"0.0001","mark_price":"367","name":"MAR_USDT","status":"trading","trade_size":21564},{"funding_next_apply":1784304000,"funding_rate":"0.0001","mark_price":"45.8","name":"XLU_USDT","status":"trading","trade_size":22073},{"funding_next_apply":1784304000,"funding_rate":"0.0001","mark_price":"7.951","name":"WEN_USDT","status":"trading","trade_size":22193},{"funding_next_apply":1784304000,"funding_rate":"0.0001","mark_price":"154.65","name":"XBI_USDT","status":"trading","trade_size":22715},{"funding_next_apply":1784304000,"funding_rate":"0.0001","mark_price":"81.21","name":"BUD_USDT","status":"trading","trade_size":23172},{"funding_next_apply":1784304000,"funding_rate":"0.0001","mark_price":"61.94","name":"BAC_USDT","status":"trading","trade_size":23591},{"funding_next_apply":1784304000,"funding_rate":"0.0001","mark_price":"44.41","name":"NKE_USDT","status":"trading","trade_size":26030},{"funding_next_apply":1784304000,"funding_rate":"0.0001","mark_price":"83.87","name":"PDD_USDT","status":"trading","trade_size":29055},{"funding_next_apply":1784304000,"funding_rate":"0.0001","mark_price":"89.86","name":"NEE_USDT","status":"trading","trade_size":29629},{"funding_next_apply":1784304000,"funding_rate":"0.0001","mark_price":"61.23","name":"AMKR_USDT","status":"trading","trade_size":29801},{"funding_next_apply":1784304000,"funding_rate":"0.0001","mark_price":"97.13","name":"SO_USDT","status":"trading","trade_size":30343},{"funding_next_apply":1784304000,"funding_rate":"0.0001","mark_price":"329.2","name":"NEURALINK_USDT","status":"trading","trade_size":32115},{"funding_next_apply":1784304000,"funding_rate":"0.0001","mark_price":"102.46","name":"SCHW_USDT","status":"trading","trade_size":32989},{"funding_next_apply":1784304000,"funding_rate":"0.0001","mark_price":"89.06","name":"WFC_USDT","status":"trading","trade_size":33098},{"funding_next_apply":1784304000,"funding_rate":"0.0001","mark_price":"57.08","name":"FOXA_USDT","status":"trading","trade_size":36420},{"funding_next_apply":1784304000,"funding_rate":"0.0001","mark_price":"235.8","name":"TTWO_USDT","status":"trading","trade_size":37360},{"funding_next_apply":1784304000,"funding_rate":"0.0001","mark_price":"108.2","name":"CVS_USDT","status":"trading","trade_size":37651},{"funding_next_apply":1784304000,"funding_rate":"0.0001","mark_price":"44.03","name":"BSX_USDT","status":"trading","trade_size":38795},{"funding_next_apply":1784304000,"funding_rate":"0.0001","mark_price":"466.2","name":"SPOT_USDT","status":"trading","trade_size":44021},{"funding_next_apply":1784304000,"funding_rate":"0.0001","mark_price":"15.21","name":"AAL_USDT","status":"trading","trade_size":44268},{"funding_next_apply":1784304000,"funding_rate":"0.0001","mark_price":"80.42","name":"MCHP_USDT","status":"trading","trade_size":45460},{"funding_next_apply":1784304000,"funding_rate":"0.0001","mark_price":"535","name":"TMO_USDT","status":"trading","trade_size":46037},{"funding_next_apply":1784304000,"funding_rate":"0.0001","mark_price":"56.69","name":"XLF_USDT","status":"trading","trade_size":48191},{"funding_next_apply":1784304000,"funding_rate":"0.0001","mark_price":"85.03","name":"STRC_USDT","status":"trading","trade_size":48759},{"funding_next_apply":1784304000,"funding_rate":"0.0001","mark_price":"301.73","name":"APD_USDT","status":"trading","trade_size":49530},{"funding_next_apply":1784304000,"funding_rate":"0.0001","mark_price":"63.28","name":"EEM_USDT","status":"trading","trade_size":51664},{"funding_next_apply":1784304000,"funding_rate":"0.0001","mark_price":"26.422","name":"CCL_USDT","status":"trading","trade_size":51708},{"funding_next_apply":1784304000,"funding_rate":"0.0001","mark_price":"522.6","name":"LIN_USDT","status":"trading","trade_size":53333},{"funding_next_apply":1784304000,"funding_rate":"0.0001","mark_price":"295.23","name":"INTU_USDT","status":"trading","trade_size":53433},{"funding_next_apply":1784304000,"funding_rate":"0.0001","mark_price":"372.8","name":"AMGN_USDT","status":"trading","trade_size":53573},{"funding_next_apply":1784304000,"funding_rate":"0.0001","mark_price":"114.85","name":"COP_USDT","status":"trading","trade_size":54927},{"funding_next_apply":1784304000,"funding_rate":"0.0001","mark_price":"24.272","name":"CMCSA_USDT","status":"trading","trade_size":55686},{"funding_next_apply":1784304000,"funding_rate":"0.0001","mark_price":"58.14","name":"FCX_USDT","status":"trading","trade_size":55851},{"funding_next_apply":1784304000,"funding_rate":"0.0001","mark_price":"38.12","name":"ASX_USDT","status":"trading","trade_size":56454},{"funding_next_apply":1784304000,"funding_rate":"0.0001","mark_price":"195.12","name":"TMUS_USDT","status":"trading","trade_size":56565},{"funding_next_apply":1784304000,"funding_rate":"0.0001","mark_price":"25.361","name":"PFE_USDT","status":"trading","trade_size":59356},{"funding_next_apply":1784304000,"funding_rate":"0.0001","mark_price":"1799.5","name":"MELI_USDT","status":"trading","trade_size":60755},{"funding_next_apply":1784304000,"funding_rate":"0.0001","mark_price":"320.9","name":"SYK_USDT","status":"trading","trade_size":62206},{"funding_next_apply":1784304000,"funding_rate":"0.0001","mark_price":"154.85","name":"TJX_USDT","status":"trading","trade_size":62233},{"funding_next_apply":1784304000,"funding_rate":"0.0001","mark_price":"1044.7","name":"GEV_USDT","status":"trading","trade_size":65008},{"funding_next_apply":1784304000,"funding_rate":"0.0001","mark_price":"146.64","name":"ABNB_USDT","status":"trading","trade_size":65074},{"funding_next_apply":1784304000,"funding_rate":"0.0001","mark_price":"208.6","name":"COF_USDT","status":"trading","trade_size":65152},{"funding_next_apply":1784304000,"funding_rate":"0.0001","mark_price":"463.3","name":"ROK_USDT","status":"trading","trade_size":67656},{"funding_next_apply":1784304000,"funding_rate":"0.0001","mark_price":"61.19","name":"STM_USDT","status":"trading","trade_size":72088},{"funding_next_apply":1784304000,"funding_rate":"0.0001","mark_price":"375.4","name":"ADI_USDT","status":"trading","trade_size":72187},{"funding_next_apply":1784304000,"funding_rate":"0.0001","mark_price":"175.56","name":"XLK_USDT","status":"trading","trade_size":72284},{"funding_next_apply":1784304000,"funding_rate":"0.0001","mark_price":"63.24","name":"CGNX_USDT","status":"trading","trade_size":73134},{"funding_next_apply":1784304000,"funding_rate":"0.0001","mark_price":"21.309","name":"SONY_USDT","status":"trading","trade_size":74796},{"funding_next_apply":1784304000,"funding_rate":"0.0001","mark_price":"366.3","name":"GLD_USDT","status":"trading","trade_size":83320},{"funding_next_apply":1784304000,"funding_rate":"0.0001","mark_price":"181.23","name":"BKNG_USDT","status":"trading","trade_size":84982},{"funding_next_apply":1784304000,"funding_rate":"0.0001","mark_price":"358.9","name":"ISRG_USDT","status":"trading","trade_size":85500},{"funding_next_apply":1784304000,"funding_rate":"0.0001","mark_price":"107.46","name":"LQD_USDT","status":"trading","trade_size":85742},{"funding_next_apply":1784304000,"funding_rate":"0.0001","mark_price":"1626.9","name":"FIX_USDT","status":"trading","trade_size":86201},{"funding_next_apply":1784304000,"funding_rate":"0.0001","mark_price":"87.93","name":"SPYM_USDT","status":"trading","trade_size":87105},{"funding_next_apply":1784304000,"funding_rate":"0.0001","mark_price":"365.16","name":"PANW_USDT","status":"trading","trade_size":98506},{"funding_next_apply":1784304000,"funding_rate":"0.0001","mark_price":"144.4","name":"ROKU_USDT","status":"trading","trade_size":102131},{"funding_next_apply":1784304000,"funding_rate":"0.0001","mark_price":"1080.2","name":"GS_USDT","status":"trading","trade_size":113264},{"funding_next_apply":1784304000,"funding_rate":"0.0001","mark_price":"35.81","name":"IBIT_USDT","status":"trading","trade_size":117591},{"funding_next_apply":1784304000,"funding_rate":"0.0001","mark_price":"44.57","name":"VZ_USDT","status":"trading","trade_size":129363},{"funding_next_apply":1784304000,"funding_rate":"0.0001","mark_price":"130.48","name":"MRK_USDT","status":"trading","trade_size":143617},{"funding_next_apply":1784304000,"funding_rate":"0.0001","mark_price":"70.79","name":"GDX_USDT","status":"trading","trade_size":146264},{"funding_next_apply":1784304000,"funding_rate":"0.0001","mark_price":"122.59","name":"SHOP_USDT","status":"trading","trade_size":153629},{"funding_next_apply":1784304000,"funding_rate":"0.0001","mark_price":"35.23","name":"EWZ_USDT","status":"trading","trade_size":157031},{"funding_next_apply":1784304000,"funding_rate":"0.0001","mark_price":"418.5","name":"APP_USDT","status":"trading","trade_size":158281},{"funding_next_apply":1784304000,"funding_rate":"0.0001","mark_price":"380.7","name":"CIEN_USDT","status":"trading","trade_size":177205},{"funding_next_apply":1784304000,"funding_rate":"0.0001","mark_price":"208.44","name":"TWLO_USDT","status":"trading","trade_size":190517},{"funding_next_apply":1784304000,"funding_rate":"0.0001","mark_price":"60.75","name":"SHLD_USDT","status":"trading","trade_size":190520},{"funding_next_apply":1784304000,"funding_rate":"0.0001","mark_price":"554.4","name":"SMH_USDT","status":"trading","trade_size":200229},{"funding_next_apply":1784304000,"funding_rate":"0.0001","mark_price":"115.72","name":"FLEX_USDT","status":"trading","trade_size":203857},{"funding_next_apply":1784304000,"funding_rate":"0.0001","mark_price":"110.59","name":"EBAY_USDT","status":"trading","trade_size":211396},{"funding_next_apply":1784304000,"funding_rate":"0.0001","mark_price":"743.6","name":"IVV_USDT","status":"trading","trade_size":212244},{"funding_next_apply":1784304000,"funding_rate":"0.0001","mark_price":"69.27","name":"CARR_USDT","status":"trading","trade_size":213397},{"funding_next_apply":1784304000,"funding_rate":"0.0001","mark_price":"649.3","name":"CMI_USDT","status":"trading","trade_size":228280},{"funding_next_apply":1784304000,"funding_rate":"0.0001","mark_price":"57.78","name":"XLE_USDT","status":"trading","trade_size":228832},{"funding_next_apply":1784304000,"funding_rate":"0.0001","mark_price":"47.96","name":"URNM_USDT","status":"trading","trade_size":230348},{"funding_next_apply":1784304000,"funding_rate":"0.0001","mark_price":"21.927","name":"GME_USDT","status":"trading","trade_size":238496},{"funding_next_apply":1784304000,"funding_rate":"0.0001","mark_price":"680.5","name":"VOO_USDT","status":"trading","trade_size":241255},{"funding_next_apply":1784304000,"funding_rate":"0.0001","mark_price":"295","name":"CLS_USDT","status":"trading","trade_size":262614},{"funding_next_apply":1784304000,"funding_rate":"0.0001","mark_price":"324.8","name":"MDB_USDT","status":"trading","trade_size":263353},{"funding_next_apply":1784304000,"funding_rate":"0.0001","mark_price":"349.6","name":"HD_USDT","status":"trading","trade_size":267350},{"funding_next_apply":1784304000,"funding_rate":"0.0001","mark_price":"469.5","name":"FN_USDT","status":"trading","trade_size":270171},{"funding_next_apply":1784304000,"funding_rate":"0.0001","mark_price":"1289.7","name":"MPWR_USDT","status":"trading","trade_size":273643},{"funding_next_apply":1784304000,"funding_rate":"0.0001","mark_price":"34.01","name":"IONQ_USDT","status":"trading","trade_size":274915},{"funding_next_apply":1784304000,"funding_rate":"0.0001","mark_price":"72.23","name":"UBER_USDT","status":"trading","trade_size":283884},{"funding_next_apply":1784304000,"funding_rate":"0.0001","mark_price":"313.9","name":"TER_USDT","status":"trading","trade_size":284226},{"funding_next_apply":1784304000,"funding_rate":"0.0001","mark_price":"254.17","name":"JNJ_USDT","status":"trading","trade_size":303089},{"funding_next_apply":1784304000,"funding_rate":"0.0001","mark_price":"42.48","name":"SQQQ_USDT","status":"trading","trade_size":313288},{"funding_next_apply":1784304000,"funding_rate":"0.0001","mark_price":"165.69","name":"ANET_USDT","status":"trading","trade_size":315579},{"funding_next_apply":1784304000,"funding_rate":"0.0001","mark_price":"152.08","name":"APH_USDT","status":"trading","trade_size":320196},{"funding_next_apply":1784304000,"funding_rate":"0.0001","mark_price":"50.73","name":"NVO_USDT","status":"trading","trade_size":331150},{"funding_next_apply":1784304000,"funding_rate":"0.0001","mark_price":"2.358","name":"GEELY_USDT","status":"trading","trade_size":334804},{"funding_next_apply":1784304000,"funding_rate":"0.0001","mark_price":"3.377","name":"TRAHK_USDT","status":"trading","trade_size":343286},{"funding_next_apply":1784304000,"funding_rate":"0.0001","mark_price":"24.402","name":"DKNG_USDT","status":"trading","trade_size":347919},{"funding_next_apply":1784304000,"funding_rate":"0.0001","mark_price":"4.998","name":"DEEPTECH_USDT","status":"trading","trade_size":350133},{"funding_next_apply":1784304000,"funding_rate":"0.0001","mark_price":"252","name":"CEG_USDT","status":"trading","trade_size":351550},{"funding_next_apply":1784304000,"funding_rate":"0.0001","mark_price":"284.4","name":"TXN_USDT","status":"trading","trade_size":352993},{"funding_next_apply":1784304000,"funding_rate":"0.0001","mark_price":"20.817","name":"POPMART_USDT","status":"trading","trade_size":355081},{"funding_next_apply":1784304000,"funding_rate":"0.0001","mark_price":"217","name":"ADSK_USDT","status":"trading","trade_size":361932},{"funding_next_apply":1784304000,"funding_rate":"0.0001","mark_price":"211.05","name":"FSLR_USDT","status":"trading","trade_size":367168}],"selection":"100_lowest_positive_trade_size","sha256":"5041b05b3df061399972c97504e81e8a32786ad660d77cf89cd89d5055c3b66c"},"thin_orderbook":{"asks":[{"p":"878.5","s":118},{"p":"880","s":112},{"p":"881.7","s":61},{"p":"882.7","s":89},{"p":"882.8","s":108},{"p":"882.9","s":99},{"p":"883","s":129},{"p":"883.1","s":104},{"p":"883.2","s":92},{"p":"883.3","s":113},{"p":"883.4","s":92},{"p":"883.5","s":108},{"p":"883.6","s":99},{"p":"883.7","s":130},{"p":"883.8","s":103},{"p":"883.9","s":133},{"p":"884","s":119},{"p":"884.1","s":119},{"p":"884.2","s":152},{"p":"884.3","s":106},{"p":"884.4","s":132},{"p":"884.5","s":110},{"p":"884.6","s":105},{"p":"884.7","s":130},{"p":"884.8","s":92},{"p":"884.9","s":107},{"p":"885","s":112},{"p":"885.1","s":111},{"p":"889.7","s":115},{"p":"889.8","s":91},{"p":"889.9","s":110},{"p":"890","s":126},{"p":"890.1","s":98},{"p":"890.2","s":104},{"p":"890.3","s":117},{"p":"890.4","s":126},{"p":"890.5","s":129},{"p":"890.6","s":116},{"p":"890.7","s":119},{"p":"890.8","s":97},{"p":"890.9","s":130},{"p":"891","s":115},{"p":"891.1","s":99},{"p":"891.2","s":100},{"p":"891.3","s":99},{"p":"891.4","s":121},{"p":"891.5","s":133},{"p":"891.6","s":106},{"p":"891.7","s":128},{"p":"891.8","s":94}],"bids":[{"p":"868.8","s":16},{"p":"868.6","s":68},{"p":"868.3","s":121},{"p":"868.2","s":112},{"p":"868.1","s":119},{"p":"868","s":116},{"p":"867.9","s":130},{"p":"867.8","s":128},{"p":"867.7","s":120},{"p":"867.6","s":120},{"p":"867.5","s":125},{"p":"867.4","s":119},{"p":"867.3","s":96},{"p":"867.2","s":119},{"p":"867.1","s":133},{"p":"867","s":99},{"p":"866.9","s":108},{"p":"866.8","s":106},{"p":"866.7","s":99},{"p":"866.6","s":93},{"p":"866.5","s":111},{"p":"866.4","s":100},{"p":"866.3","s":137},{"p":"866.2","s":116},{"p":"866.1","s":101},{"p":"866","s":127},{"p":"865.9","s":110},{"p":"861.8","s":1},{"p":"861.3","s":103},{"p":"861.2","s":129},{"p":"861.1","s":97},{"p":"861","s":96},{"p":"860.9","s":105},{"p":"860.8","s":95},{"p":"860.7","s":113},{"p":"860.6","s":137},{"p":"860.5","s":104},{"p":"860.4","s":101},{"p":"860.3","s":110},{"p":"860.2","s":102},{"p":"860.1","s":95},{"p":"860","s":114},{"p":"859.9","s":95},{"p":"859.8","s":126},{"p":"859.7","s":118},{"p":"859.6","s":128},{"p":"859.5","s":139},{"p":"859.4","s":110},{"p":"859.3","s":132},{"p":"859.2","s":104}],"contract":"CAT_USDT","exchange":"gateio","selection":"lowest_positive_trade_size","sha256":"253e4cc7967c1df17406ae4c4f7a00358917cfb9e53acde7a7fb46b2bfcf5d8a"}}}
