{"observed_at":"2026-07-13T04:47:00Z","sources":{"point_in_time_token_list":{"added":["1-is-all-you-need-2"],"current_path":"current/token_list.json","record_count":17528,"removed":["1-is-all-you-need","bycocket"],"sha256":"2392c6a75ca18e3709cbeeaf5beb3e37a8d4a1e16439eb46eefb3562fc117820"},"small_exchange_funding":{"exchange":"gateio","records":[{"funding_next_apply":1783929600,"funding_rate":"0.0001","mark_price":"947.1","name":"CAT_USDT","status":"trading","trade_size":8125},{"funding_next_apply":1783929600,"funding_rate":"0.0001","mark_price":"59.76","name":"BAC_USDT","status":"trading","trade_size":11990},{"funding_next_apply":1783929600,"funding_rate":"0.0001","mark_price":"45.21","name":"XLU_USDT","status":"trading","trade_size":13947},{"funding_next_apply":1783929600,"funding_rate":"0.0001","mark_price":"7.535","name":"WEN_USDT","status":"trading","trade_size":14153},{"funding_next_apply":1783929600,"funding_rate":"0.0001","mark_price":"376","name":"MAR_USDT","status":"trading","trade_size":14385},{"funding_next_apply":1783929600,"funding_rate":"0.0001","mark_price":"79.66","name":"BUD_USDT","status":"trading","trade_size":17265},{"funding_next_apply":1783929600,"funding_rate":"0.0001","mark_price":"44.31","name":"NKE_USDT","status":"trading","trade_size":18708},{"funding_next_apply":1783929600,"funding_rate":"0.0001","mark_price":"69.61","name":"AMKR_USDT","status":"trading","trade_size":21395},{"funding_next_apply":1783929600,"funding_rate":"0.0001","mark_price":"85.07","name":"PDD_USDT","status":"trading","trade_size":22062},{"funding_next_apply":1783929600,"funding_rate":"0.0001","mark_price":"88.07","name":"NEE_USDT","status":"trading","trade_size":24782},{"funding_next_apply":1783929600,"funding_rate":"0.0001","mark_price":"95.62","name":"SO_USDT","status":"trading","trade_size":25322},{"funding_next_apply":1783929600,"funding_rate":"0.0001","mark_price":"53.82","name":"FOXA_USDT","status":"trading","trade_size":25841},{"funding_next_apply":1783929600,"funding_rate":"0.0001","mark_price":"243.6","name":"TTWO_USDT","status":"trading","trade_size":26850},{"funding_next_apply":1783929600,"funding_rate":"0.0001","mark_price":"87.16","name":"WFC_USDT","status":"trading","trade_size":27299},{"funding_next_apply":1783929600,"funding_rate":"0.0001","mark_price":"102.98","name":"SCHW_USDT","status":"trading","trade_size":28250},{"funding_next_apply":1783929600,"funding_rate":"0.0001","mark_price":"29.45","name":"KSTR_USDT","status":"trading","trade_size":30772},{"funding_next_apply":1783929600,"funding_rate":"0.0001","mark_price":"44.77","name":"BSX_USDT","status":"trading","trade_size":31175},{"funding_next_apply":1783929600,"funding_rate":"0.0001","mark_price":"104.24","name":"CVS_USDT","status":"trading","trade_size":34209},{"funding_next_apply":1783929600,"funding_rate":"0.0001","mark_price":"16.891","name":"AAL_USDT","status":"trading","trade_size":36422},{"funding_next_apply":1783929600,"funding_rate":"0.0001","mark_price":"298.62","name":"APD_USDT","status":"trading","trade_size":37032},{"funding_next_apply":1783929600,"funding_rate":"0.0001","mark_price":"480.1","name":"SPOT_USDT","status":"trading","trade_size":38073},{"funding_next_apply":1783929600,"funding_rate":"0.0001","mark_price":"88.66","name":"MCHP_USDT","status":"trading","trade_size":38113},{"funding_next_apply":1783929600,"funding_rate":"0.0001","mark_price":"87.9","name":"STRC_USDT","status":"trading","trade_size":39894},{"funding_next_apply":1783929600,"funding_rate":"0.0001","mark_price":"526.9","name":"TMO_USDT","status":"trading","trade_size":40174},{"funding_next_apply":1783929600,"funding_rate":"0.0001","mark_price":"55.73","name":"XLF_USDT","status":"trading","trade_size":41076},{"funding_next_apply":1783929600,"funding_rate":"0.0001","mark_price":"110.05","name":"COP_USDT","status":"trading","trade_size":41458},{"funding_next_apply":1783929600,"funding_rate":"0.0001","mark_price":"1863","name":"MELI_USDT","status":"trading","trade_size":42888},{"funding_next_apply":1783929600,"funding_rate":"0.0001","mark_price":"42.36","name":"ASX_USDT","status":"trading","trade_size":43143},{"funding_next_apply":1783929600,"funding_rate":"0.0001","mark_price":"66.84","name":"EEM_USDT","status":"trading","trade_size":43518},{"funding_next_apply":1783929600,"funding_rate":"0.0001","mark_price":"26.801","name":"CCL_USDT","status":"trading","trade_size":44443},{"funding_next_apply":1783929600,"funding_rate":"0.0001","mark_price":"274.95","name":"INTU_USDT","status":"trading","trade_size":44873},{"funding_next_apply":1783929600,"funding_rate":"0.0001","mark_price":"23.613","name":"CMCSA_USDT","status":"trading","trade_size":45822},{"funding_next_apply":1783929600,"funding_rate":"0.0001","mark_price":"363.9","name":"AMGN_USDT","status":"trading","trade_size":46624},{"funding_next_apply":1783929600,"funding_rate":"0.0001","mark_price":"531","name":"LIN_USDT","status":"trading","trade_size":47117},{"funding_next_apply":1783929600,"funding_rate":"0.0001","mark_price":"218.9","name":"TSEM_USDT","status":"trading","trade_size":47761},{"funding_next_apply":1783929600,"funding_rate":"0.0001","mark_price":"187.91","name":"TMUS_USDT","status":"trading","trade_size":48727},{"funding_next_apply":1783929600,"funding_rate":"0.0001","mark_price":"71.57","name":"STM_USDT","status":"trading","trade_size":49968},{"funding_next_apply":1783929600,"funding_rate":"0.0001","mark_price":"61.7","name":"FCX_USDT","status":"trading","trade_size":50098},{"funding_next_apply":1783929600,"funding_rate":"0.0001","mark_price":"24.311","name":"PFE_USDT","status":"trading","trade_size":51611},{"funding_next_apply":1783929600,"funding_rate":"0.0001","mark_price":"151.43","name":"TJX_USDT","status":"trading","trade_size":51861},{"funding_next_apply":1783929600,"funding_rate":"0.0001","mark_price":"328.9","name":"SYK_USDT","status":"trading","trade_size":52719},{"funding_next_apply":1783929600,"funding_rate":"0.0001","mark_price":"200.9","name":"COF_USDT","status":"trading","trade_size":53685},{"funding_next_apply":1783929600,"funding_rate":"0.0001","mark_price":"148.22","name":"ABNB_USDT","status":"trading","trade_size":56066},{"funding_next_apply":1783929600,"funding_rate":"0.0001","mark_price":"1076.3","name":"GEV_USDT","status":"trading","trade_size":57745},{"funding_next_apply":1783929600,"funding_rate":"0.0001","mark_price":"1763.3","name":"FIX_USDT","status":"trading","trade_size":59284},{"funding_next_apply":1783929600,"funding_rate":"0.0001","mark_price":"475","name":"ROK_USDT","status":"trading","trade_size":60328},{"funding_next_apply":1783929600,"funding_rate":"0.0001","mark_price":"20.536","name":"SONY_USDT","status":"trading","trade_size":60952},{"funding_next_apply":1783929600,"funding_rate":"0.0001","mark_price":"75.24","name":"GDX_USDT","status":"trading","trade_size":61360},{"funding_next_apply":1783929600,"funding_rate":"0.0001","mark_price":"184.32","name":"XLK_USDT","status":"trading","trade_size":62253},{"funding_next_apply":1783929600,"funding_rate":"0.0001","mark_price":"394.8","name":"ADI_USDT","status":"trading","trade_size":64284},{"funding_next_apply":1783929600,"funding_rate":"0.0001","mark_price":"407.9","name":"ISRG_USDT","status":"trading","trade_size":64396},{"funding_next_apply":1783929600,"funding_rate":"0.0001","mark_price":"66.85","name":"CGNX_USDT","status":"trading","trade_size":65998},{"funding_next_apply":1783929600,"funding_rate":"0.0001","mark_price":"372","name":"GLD_USDT","status":"trading","trade_size":66333},{"funding_next_apply":1783929600,"funding_rate":"0.0001","mark_price":"107.4","name":"LQD_USDT","status":"trading","trade_size":73260},{"funding_next_apply":1783929600,"funding_rate":"0.0001","mark_price":"178.27","name":"BKNG_USDT","status":"trading","trade_size":76173},{"funding_next_apply":1783929600,"funding_rate":"0.0001","mark_price":"347.4","name":"TER_USDT","status":"trading","trade_size":77292},{"funding_next_apply":1783929600,"funding_rate":"0.0001","mark_price":"88.89","name":"SPYM_USDT","status":"trading","trade_size":79417},{"funding_next_apply":1783929600,"funding_rate":"0.0001","mark_price":"140.78","name":"ROKU_USDT","status":"trading","trade_size":83444},{"funding_next_apply":1783929600,"funding_rate":"0.0001","mark_price":"323.67","name":"PANW_USDT","status":"trading","trade_size":86442},{"funding_next_apply":1783929600,"funding_rate":"0.0001","mark_price":"1061.1","name":"GS_USDT","status":"trading","trade_size":93869},{"funding_next_apply":1783929600,"funding_rate":"0.0001","mark_price":"304.9","name":"TXN_USDT","status":"trading","trade_size":98560},{"funding_next_apply":1783929600,"funding_rate":"-0.0002","mark_price":"748.8","name":"IVV_USDT","status":"trading","trade_size":98843},{"funding_next_apply":1783929600,"funding_rate":"0.0001","mark_price":"42.7","name":"IONQ_USDT","status":"trading","trade_size":98921},{"funding_next_apply":1783929600,"funding_rate":"0.0001","mark_price":"123.48","name":"MRK_USDT","status":"trading","trade_size":100840},{"funding_next_apply":1783929600,"funding_rate":"0.0001","mark_price":"208.02","name":"ADSK_USDT","status":"trading","trade_size":101247},{"funding_next_apply":1783929600,"funding_rate":"0.0001","mark_price":"35.84","name":"IBIT_USDT","status":"trading","trade_size":108869},{"funding_next_apply":1783929600,"funding_rate":"0.0001","mark_price":"42.18","name":"VZ_USDT","status":"trading","trade_size":122211},{"funding_next_apply":1783929600,"funding_rate":"0.0001","mark_price":"35.67","name":"EWZ_USDT","status":"trading","trade_size":125489},{"funding_next_apply":1783929600,"funding_rate":"0.0001","mark_price":"32.1","name":"BSP_USDT","status":"trading","trade_size":132231},{"funding_next_apply":1783929600,"funding_rate":"0.0001","mark_price":"122.79","name":"SHOP_USDT","status":"trading","trade_size":137831},{"funding_next_apply":1783929600,"funding_rate":"0.0001","mark_price":"447.4","name":"CIEN_USDT","status":"trading","trade_size":142439},{"funding_next_apply":1783929600,"funding_rate":"-0.000135","mark_price":"133.83","name":"FLEX_USDT","status":"trading","trade_size":163652},{"funding_next_apply":1783929600,"funding_rate":"0.0001","mark_price":"39.21","name":"SQQQ_USDT","status":"trading","trade_size":164653},{"funding_next_apply":1783929600,"funding_rate":"0.0001","mark_price":"74.41","name":"UBER_USDT","status":"trading","trade_size":168890},{"funding_next_apply":1783929600,"funding_rate":"0.0001","mark_price":"598.8","name":"SMH_USDT","status":"trading","trade_size":172486},{"funding_next_apply":1783929600,"funding_rate":"0.0001","mark_price":"213.67","name":"TWLO_USDT","status":"trading","trade_size":176958},{"funding_next_apply":1783929600,"funding_rate":"0.0001","mark_price":"117.6","name":"EBAY_USDT","status":"trading","trade_size":178722},{"funding_next_apply":1783929600,"funding_rate":"0.0001","mark_price":"61.08","name":"SHLD_USDT","status":"trading","trade_size":181409},{"funding_next_apply":1783929600,"funding_rate":"0.0001","mark_price":"688.3","name":"VOO_USDT","status":"trading","trade_size":190139},{"funding_next_apply":1783929600,"funding_rate":"0.0001","mark_price":"334.2","name":"LRCX_USDT","status":"trading","trade_size":206318},{"funding_next_apply":1783929600,"funding_rate":"0.0001","mark_price":"70.09","name":"CARR_USDT","status":"trading","trade_size":207697},{"funding_next_apply":1783929600,"funding_rate":"0.0001","mark_price":"32.08","name":"MVLL_USDT","status":"trading","trade_size":209627},{"funding_next_apply":1783929600,"funding_rate":"0.0001","mark_price":"52.73","name":"URNM_USDT","status":"trading","trade_size":211764},{"funding_next_apply":1783929600,"funding_rate":"0.0001","mark_price":"55.75","name":"XLE_USDT","status":"trading","trade_size":216084},{"funding_next_apply":1783929600,"funding_rate":"0.0001","mark_price":"674","name":"CMI_USDT","status":"trading","trade_size":221263},{"funding_next_apply":1783929600,"funding_rate":"0.0001","mark_price":"21.63","name":"GME_USDT","status":"trading","trade_size":227793},{"funding_next_apply":1783929600,"funding_rate":"0.0001","mark_price":"1361","name":"MPWR_USDT","status":"trading","trade_size":243249},{"funding_next_apply":1783929600,"funding_rate":"0.0001","mark_price":"465.9","name":"FN_USDT","status":"trading","trade_size":251406},{"funding_next_apply":1783929600,"funding_rate":"0.0001","mark_price":"361","name":"CLS_USDT","status":"trading","trade_size":253505},{"funding_next_apply":1783929600,"funding_rate":"0.0001","mark_price":"341.3","name":"MDB_USDT","status":"trading","trade_size":254475},{"funding_next_apply":1783929600,"funding_rate":"0.0001","mark_price":"341.9","name":"HD_USDT","status":"trading","trade_size":257685},{"funding_next_apply":1783929600,"funding_rate":"0.0001","mark_price":"26.394","name":"DKNG_USDT","status":"trading","trade_size":274336},{"funding_next_apply":1783929600,"funding_rate":"0.0001","mark_price":"258.02","name":"JNJ_USDT","status":"trading","trade_size":281816},{"funding_next_apply":1783929600,"funding_rate":"0.0001","mark_price":"186.71","name":"ANET_USDT","status":"trading","trade_size":300148},{"funding_next_apply":1783929600,"funding_rate":"0.0001","mark_price":"223.7","name":"ADBE_USDT","status":"trading","trade_size":305524},{"funding_next_apply":1783929600,"funding_rate":"0.0001","mark_price":"395.2","name":"ALAB_USDT","status":"trading","trade_size":307732},{"funding_next_apply":1783929600,"funding_rate":"0.0001","mark_price":"159.1","name":"APH_USDT","status":"trading","trade_size":310320},{"funding_next_apply":1783929600,"funding_rate":"0.0001","mark_price":"49.48","name":"NVO_USDT","status":"trading","trade_size":319723},{"funding_next_apply":1783929600,"funding_rate":"0.0001","mark_price":"19.635","name":"POPMART_USDT","status":"trading","trade_size":323236},{"funding_next_apply":1783929600,"funding_rate":"0.0001","mark_price":"562.7","name":"SOXX_USDT","status":"trading","trade_size":323921}],"selection":"100_lowest_positive_trade_size","sha256":"b4cc8bb761147ad2783a5ec0718af93b14e4bc81e97f244cd0895845c97f530d"},"thin_orderbook":{"asks":[{"p":"954.8","s":28},{"p":"954.9","s":35},{"p":"955","s":34},{"p":"955.1","s":30},{"p":"955.2","s":26},{"p":"955.3","s":31},{"p":"955.4","s":28},{"p":"955.5","s":29},{"p":"955.6","s":36},{"p":"955.7","s":29},{"p":"955.8","s":31},{"p":"955.9","s":28},{"p":"956","s":28},{"p":"956.1","s":26},{"p":"956.2","s":31},{"p":"956.3","s":33},{"p":"956.4","s":36},{"p":"956.5","s":26},{"p":"956.6","s":31},{"p":"956.7","s":30},{"p":"956.8","s":26},{"p":"956.9","s":29},{"p":"957","s":28},{"p":"957.1","s":26},{"p":"957.2","s":31},{"p":"970.9","s":17},{"p":"971","s":22},{"p":"971.1","s":20},{"p":"971.2","s":21},{"p":"971.3","s":18},{"p":"971.4","s":21},{"p":"971.5","s":24},{"p":"971.6","s":21},{"p":"971.7","s":23},{"p":"971.8","s":18},{"p":"971.9","s":18},{"p":"972","s":22},{"p":"972.1","s":21},{"p":"972.2","s":24},{"p":"972.3","s":19},{"p":"972.4","s":24},{"p":"972.5","s":24},{"p":"972.6","s":17},{"p":"972.7","s":17},{"p":"972.8","s":20},{"p":"972.9","s":19},{"p":"973","s":21},{"p":"973.1","s":21},{"p":"973.2","s":17},{"p":"973.3","s":17}],"bids":[{"p":"939.4","s":32},{"p":"939.3","s":27},{"p":"939.2","s":34},{"p":"939.1","s":37},{"p":"939","s":29},{"p":"938.9","s":34},{"p":"938.8","s":35},{"p":"938.7","s":30},{"p":"938.6","s":37},{"p":"938.5","s":34},{"p":"938.4","s":36},{"p":"938.3","s":35},{"p":"938.2","s":38},{"p":"938.1","s":33},{"p":"938","s":28},{"p":"937.9","s":27},{"p":"937.8","s":30},{"p":"937.7","s":30},{"p":"937.6","s":31},{"p":"937.5","s":31},{"p":"937.4","s":34},{"p":"937.3","s":29},{"p":"937.2","s":34},{"p":"937.1","s":36},{"p":"937","s":36},{"p":"927.4","s":1},{"p":"923.5","s":1},{"p":"923.4","s":491},{"p":"923.3","s":19},{"p":"923.2","s":19},{"p":"923.1","s":25},{"p":"923","s":24},{"p":"922.9","s":19},{"p":"922.8","s":20},{"p":"922.7","s":20},{"p":"922.6","s":25},{"p":"922.5","s":23},{"p":"922.4","s":25},{"p":"922.3","s":21},{"p":"922.2","s":24},{"p":"922.1","s":23},{"p":"922","s":20},{"p":"921.9","s":18},{"p":"921.8","s":20},{"p":"921.7","s":25},{"p":"921.6","s":21},{"p":"921.5","s":23},{"p":"921.4","s":18},{"p":"921.3","s":18},{"p":"921.2","s":18}],"contract":"CAT_USDT","exchange":"gateio","selection":"lowest_positive_trade_size","sha256":"edd9ffc8aef74a15c73389e2c537e85ab35cafa20db35dd2b048087077add354"}}}
