{"observed_at":"2026-07-18T03:00:00Z","sources":{"point_in_time_token_list":{"added":[],"current_path":"current/token_list.json","record_count":17632,"removed":[],"sha256":"49a62357c027b98e9d083b3c86d5f2110c6e7c53193545112fedc4c8b863f606"},"small_exchange_funding":{"exchange":"gateio","records":[{"funding_next_apply":1784361600,"funding_rate":"0.0001","mark_price":"879.3","name":"CAT_USDT","status":"trading","trade_size":18434},{"funding_next_apply":1784361600,"funding_rate":"0.0001","mark_price":"366.4","name":"MAR_USDT","status":"trading","trade_size":22326},{"funding_next_apply":1784361600,"funding_rate":"0.0001","mark_price":"45.29","name":"XLU_USDT","status":"trading","trade_size":23222},{"funding_next_apply":1784361600,"funding_rate":"0.0001","mark_price":"80.54","name":"BUD_USDT","status":"trading","trade_size":23753},{"funding_next_apply":1784361600,"funding_rate":"0.0001","mark_price":"61.31","name":"BAC_USDT","status":"trading","trade_size":24148},{"funding_next_apply":1784361600,"funding_rate":"0.0001","mark_price":"7.727","name":"WEN_USDT","status":"trading","trade_size":24858},{"funding_next_apply":1784361600,"funding_rate":"0.0001","mark_price":"43.81","name":"NKE_USDT","status":"trading","trade_size":26715},{"funding_next_apply":1784361600,"funding_rate":"0.0001","mark_price":"154.67","name":"XBI_USDT","status":"trading","trade_size":27319},{"funding_next_apply":1784361600,"funding_rate":"0.0001","mark_price":"84.7","name":"PDD_USDT","status":"trading","trade_size":29791},{"funding_next_apply":1784361600,"funding_rate":"0.0001","mark_price":"88.75","name":"NEE_USDT","status":"trading","trade_size":30254},{"funding_next_apply":1784361600,"funding_rate":"0.0001","mark_price":"95.87","name":"SO_USDT","status":"trading","trade_size":30709},{"funding_next_apply":1784361600,"funding_rate":"0.0001","mark_price":"62.99","name":"AMKR_USDT","status":"trading","trade_size":30758},{"funding_next_apply":1784361600,"funding_rate":"0.0001","mark_price":"317.86","name":"NEURALINK_USDT","status":"trading","trade_size":32851},{"funding_next_apply":1784361600,"funding_rate":"0.0001","mark_price":"101.8","name":"SCHW_USDT","status":"trading","trade_size":33670},{"funding_next_apply":1784361600,"funding_rate":"0.0001","mark_price":"87.48","name":"WFC_USDT","status":"trading","trade_size":33743},{"funding_next_apply":1784361600,"funding_rate":"0.0001","mark_price":"57.5","name":"FOXA_USDT","status":"trading","trade_size":37006},{"funding_next_apply":1784361600,"funding_rate":"0.0001","mark_price":"107.55","name":"CVS_USDT","status":"trading","trade_size":38061},{"funding_next_apply":1784361600,"funding_rate":"0.0001","mark_price":"237.6","name":"TTWO_USDT","status":"trading","trade_size":38376},{"funding_next_apply":1784361600,"funding_rate":"0.0001","mark_price":"44.08","name":"BSX_USDT","status":"trading","trade_size":39794},{"funding_next_apply":1784361600,"funding_rate":"0.0001","mark_price":"474.3","name":"SPOT_USDT","status":"trading","trade_size":44785},{"funding_next_apply":1784361600,"funding_rate":"0.0001","mark_price":"15.027","name":"AAL_USDT","status":"trading","trade_size":45113},{"funding_next_apply":1784361600,"funding_rate":"0.0001","mark_price":"80.96","name":"MCHP_USDT","status":"trading","trade_size":45919},{"funding_next_apply":1784361600,"funding_rate":"0.0001","mark_price":"532.6","name":"TMO_USDT","status":"trading","trade_size":46657},{"funding_next_apply":1784361600,"funding_rate":"0.0001","mark_price":"56.36","name":"XLF_USDT","status":"trading","trade_size":49034},{"funding_next_apply":1784361600,"funding_rate":"0.0001","mark_price":"85.51","name":"STRC_USDT","status":"trading","trade_size":49507},{"funding_next_apply":1784361600,"funding_rate":"0.0001","mark_price":"297.32","name":"APD_USDT","status":"trading","trade_size":50443},{"funding_next_apply":1784361600,"funding_rate":"0.0001","mark_price":"63.54","name":"EEM_USDT","status":"trading","trade_size":52241},{"funding_next_apply":1784361600,"funding_rate":"0.0001","mark_price":"26.427","name":"CCL_USDT","status":"trading","trade_size":52737},{"funding_next_apply":1784361600,"funding_rate":"0.0001","mark_price":"514.6","name":"LIN_USDT","status":"trading","trade_size":53962},{"funding_next_apply":1784361600,"funding_rate":"0.0001","mark_price":"367.3","name":"AMGN_USDT","status":"trading","trade_size":54510},{"funding_next_apply":1784361600,"funding_rate":"0.0001","mark_price":"291.13","name":"INTU_USDT","status":"trading","trade_size":54603},{"funding_next_apply":1784361600,"funding_rate":"0.0001","mark_price":"58.42","name":"FCX_USDT","status":"trading","trade_size":56453},{"funding_next_apply":1784361600,"funding_rate":"0.0001","mark_price":"23.833","name":"CMCSA_USDT","status":"trading","trade_size":56487},{"funding_next_apply":1784361600,"funding_rate":"0.0001","mark_price":"38.4","name":"ASX_USDT","status":"trading","trade_size":57212},{"funding_next_apply":1784361600,"funding_rate":"0.0001","mark_price":"192.41","name":"TMUS_USDT","status":"trading","trade_size":57815},{"funding_next_apply":1784361600,"funding_rate":"0.0001","mark_price":"25.098","name":"PFE_USDT","status":"trading","trade_size":60287},{"funding_next_apply":1784361600,"funding_rate":"0.0001","mark_price":"1809.3","name":"MELI_USDT","status":"trading","trade_size":61592},{"funding_next_apply":1784361600,"funding_rate":"0.0001","mark_price":"320.3","name":"SYK_USDT","status":"trading","trade_size":63055},{"funding_next_apply":1784361600,"funding_rate":"0.0001","mark_price":"155.27","name":"TJX_USDT","status":"trading","trade_size":63074},{"funding_next_apply":1784361600,"funding_rate":"-0.0002","mark_price":"114.82","name":"COP_USDT","status":"trading","trade_size":64832},{"funding_next_apply":1784361600,"funding_rate":"0.0001","mark_price":"1056.2","name":"GEV_USDT","status":"trading","trade_size":65459},{"funding_next_apply":1784361600,"funding_rate":"0.0001","mark_price":"145.89","name":"ABNB_USDT","status":"trading","trade_size":65924},{"funding_next_apply":1784361600,"funding_rate":"0.0001","mark_price":"208.16","name":"COF_USDT","status":"trading","trade_size":65984},{"funding_next_apply":1784361600,"funding_rate":"0.0001","mark_price":"462.5","name":"ROK_USDT","status":"trading","trade_size":68493},{"funding_next_apply":1784361600,"funding_rate":"0.0001","mark_price":"375.4","name":"ADI_USDT","status":"trading","trade_size":73028},{"funding_next_apply":1784361600,"funding_rate":"0.0001","mark_price":"175.55","name":"XLK_USDT","status":"trading","trade_size":73273},{"funding_next_apply":1784361600,"funding_rate":"0.0001","mark_price":"64.16","name":"CGNX_USDT","status":"trading","trade_size":73714},{"funding_next_apply":1784361600,"funding_rate":"0.0001","mark_price":"61.97","name":"STM_USDT","status":"trading","trade_size":74084},{"funding_next_apply":1784361600,"funding_rate":"0.0001","mark_price":"21.042","name":"SONY_USDT","status":"trading","trade_size":76122},{"funding_next_apply":1784361600,"funding_rate":"0.0001","mark_price":"370.3","name":"GLD_USDT","status":"trading","trade_size":84088},{"funding_next_apply":1784361600,"funding_rate":"0.0001","mark_price":"181.74","name":"BKNG_USDT","status":"trading","trade_size":85814},{"funding_next_apply":1784361600,"funding_rate":"0.0001","mark_price":"107.21","name":"LQD_USDT","status":"trading","trade_size":86770},{"funding_next_apply":1784361600,"funding_rate":"0.0001","mark_price":"347.1","name":"ISRG_USDT","status":"trading","trade_size":86896},{"funding_next_apply":1784361600,"funding_rate":"0.0001","mark_price":"1669.4","name":"FIX_USDT","status":"trading","trade_size":87652},{"funding_next_apply":1784361600,"funding_rate":"0.0001","mark_price":"87.56","name":"SPYM_USDT","status":"trading","trade_size":87716},{"funding_next_apply":1784361600,"funding_rate":"0.0001","mark_price":"355.59","name":"PANW_USDT","status":"trading","trade_size":99265},{"funding_next_apply":1784361600,"funding_rate":"0.0001","mark_price":"144.01","name":"ROKU_USDT","status":"trading","trade_size":103324},{"funding_next_apply":1784361600,"funding_rate":"0.0001","mark_price":"1067.6","name":"GS_USDT","status":"trading","trade_size":114314},{"funding_next_apply":1784361600,"funding_rate":"0.0001","mark_price":"36.32","name":"IBIT_USDT","status":"trading","trade_size":119001},{"funding_next_apply":1784361600,"funding_rate":"0.0001","mark_price":"43.66","name":"VZ_USDT","status":"trading","trade_size":130057},{"funding_next_apply":1784361600,"funding_rate":"0.0001","mark_price":"127.91","name":"MRK_USDT","status":"trading","trade_size":145349},{"funding_next_apply":1784361600,"funding_rate":"0.0001","mark_price":"123.59","name":"SHOP_USDT","status":"trading","trade_size":154483},{"funding_next_apply":1784361600,"funding_rate":"0.0001","mark_price":"35.46","name":"EWZ_USDT","status":"trading","trade_size":158165},{"funding_next_apply":1784361600,"funding_rate":"0.0001","mark_price":"71.66","name":"GDX_USDT","status":"trading","trade_size":162971},{"funding_next_apply":1784361600,"funding_rate":"0.0001","mark_price":"371.1","name":"CIEN_USDT","status":"trading","trade_size":178008},{"funding_next_apply":1784361600,"funding_rate":"0.0001","mark_price":"425.2","name":"APP_USDT","status":"trading","trade_size":185364},{"funding_next_apply":1784361600,"funding_rate":"0.0001","mark_price":"61.58","name":"SHLD_USDT","status":"trading","trade_size":191665},{"funding_next_apply":1784361600,"funding_rate":"0.0001","mark_price":"205.67","name":"TWLO_USDT","status":"trading","trade_size":191973},{"funding_next_apply":1784361600,"funding_rate":"0.0001","mark_price":"555.2","name":"SMH_USDT","status":"trading","trade_size":201401},{"funding_next_apply":1784361600,"funding_rate":"0.0001","mark_price":"119.33","name":"FLEX_USDT","status":"trading","trade_size":205050},{"funding_next_apply":1784361600,"funding_rate":"0.0001","mark_price":"112.36","name":"EBAY_USDT","status":"trading","trade_size":212380},{"funding_next_apply":1784361600,"funding_rate":"0.0001","mark_price":"68.87","name":"CARR_USDT","status":"trading","trade_size":213929},{"funding_next_apply":1784361600,"funding_rate":"0.0001","mark_price":"743.3","name":"IVV_USDT","status":"trading","trade_size":222636},{"funding_next_apply":1784361600,"funding_rate":"0.0001","mark_price":"648.2","name":"CMI_USDT","status":"trading","trade_size":229142},{"funding_next_apply":1784361600,"funding_rate":"0.0001","mark_price":"58.21","name":"XLE_USDT","status":"trading","trade_size":229771},{"funding_next_apply":1784361600,"funding_rate":"0.0001","mark_price":"48.7","name":"URNM_USDT","status":"trading","trade_size":231858},{"funding_next_apply":1784361600,"funding_rate":"0.0001","mark_price":"22.026","name":"GME_USDT","status":"trading","trade_size":239734},{"funding_next_apply":1784361600,"funding_rate":"0.0001","mark_price":"680.2","name":"VOO_USDT","status":"trading","trade_size":252338},{"funding_next_apply":1784361600,"funding_rate":"0.0001","mark_price":"311.5","name":"MDB_USDT","status":"trading","trade_size":264160},{"funding_next_apply":1784361600,"funding_rate":"0.0001","mark_price":"299.4","name":"CLS_USDT","status":"trading","trade_size":266163},{"funding_next_apply":1784361600,"funding_rate":"0.0001","mark_price":"339","name":"HD_USDT","status":"trading","trade_size":270509},{"funding_next_apply":1784361600,"funding_rate":"0.0001","mark_price":"474.4","name":"FN_USDT","status":"trading","trade_size":272542},{"funding_next_apply":1784361600,"funding_rate":"0.0001","mark_price":"1311.1","name":"MPWR_USDT","status":"trading","trade_size":274550},{"funding_next_apply":1784361600,"funding_rate":"0.0001","mark_price":"35.1","name":"IONQ_USDT","status":"trading","trade_size":291833},{"funding_next_apply":1784361600,"funding_rate":"0.0001","mark_price":"321.5","name":"TER_USDT","status":"trading","trade_size":293628},{"funding_next_apply":1784361600,"funding_rate":"0.0001","mark_price":"72.68","name":"UBER_USDT","status":"trading","trade_size":300005},{"funding_next_apply":1784361600,"funding_rate":"0.0001","mark_price":"254.85","name":"JNJ_USDT","status":"trading","trade_size":306457},{"funding_next_apply":1784361600,"funding_rate":"0.0001","mark_price":"168.82","name":"ANET_USDT","status":"trading","trade_size":316637},{"funding_next_apply":1784361600,"funding_rate":"0.0001","mark_price":"152.72","name":"APH_USDT","status":"trading","trade_size":321977},{"funding_next_apply":1784361600,"funding_rate":"0.0001","mark_price":"42.78","name":"SQQQ_USDT","status":"trading","trade_size":326330},{"funding_next_apply":1784361600,"funding_rate":"0.0001","mark_price":"50.39","name":"NVO_USDT","status":"trading","trade_size":335262},{"funding_next_apply":1784361600,"funding_rate":"0.0001","mark_price":"2.354","name":"GEELY_USDT","status":"trading","trade_size":335599},{"funding_next_apply":1784361600,"funding_rate":"0.0001","mark_price":"3.377","name":"TRAHK_USDT","status":"trading","trade_size":344035},{"funding_next_apply":1784361600,"funding_rate":"0.0001","mark_price":"4.966","name":"DEEPTECH_USDT","status":"trading","trade_size":350804},{"funding_next_apply":1784361600,"funding_rate":"0.0001","mark_price":"253.1","name":"CEG_USDT","status":"trading","trade_size":352605},{"funding_next_apply":1784361600,"funding_rate":"0.0001","mark_price":"24.832","name":"DKNG_USDT","status":"trading","trade_size":354523},{"funding_next_apply":1784361600,"funding_rate":"0.0001","mark_price":"20.662","name":"POPMART_USDT","status":"trading","trade_size":356435},{"funding_next_apply":1784361600,"funding_rate":"0.0001","mark_price":"213.26","name":"FSLR_USDT","status":"trading","trade_size":368269},{"funding_next_apply":1784361600,"funding_rate":"0.0001","mark_price":"359.6","name":"V_USDT","status":"trading","trade_size":372979},{"funding_next_apply":1784361600,"funding_rate":"0.0001","mark_price":"173.3","name":"BWXT_USDT","status":"trading","trade_size":374966}],"selection":"100_lowest_positive_trade_size","sha256":"294e82fb381d21fb316dd7500c399629299d089ea04067c8ab009f3342c0f2e5"},"thin_orderbook":{"asks":[{"p":"882.8","s":13},{"p":"882.9","s":27},{"p":"893.1","s":30},{"p":"893.2","s":31},{"p":"893.3","s":37},{"p":"893.4","s":36},{"p":"893.5","s":21},{"p":"893.6","s":18},{"p":"893.7","s":39},{"p":"893.8","s":30},{"p":"893.9","s":34},{"p":"894","s":32},{"p":"894.1","s":32},{"p":"894.2","s":29},{"p":"894.3","s":36},{"p":"894.4","s":33},{"p":"894.5","s":27},{"p":"894.6","s":38},{"p":"894.7","s":38},{"p":"894.8","s":32},{"p":"894.9","s":35},{"p":"895","s":27},{"p":"895.1","s":30},{"p":"895.2","s":39},{"p":"895.3","s":38},{"p":"895.4","s":33},{"p":"895.5","s":25},{"p":"901.2","s":516},{"p":"901.5","s":18},{"p":"901.6","s":24},{"p":"901.7","s":23},{"p":"901.8","s":21},{"p":"901.9","s":26},{"p":"902","s":24},{"p":"902.1","s":26},{"p":"902.2","s":22},{"p":"902.3","s":22},{"p":"902.4","s":24},{"p":"902.5","s":23},{"p":"902.6","s":26},{"p":"902.7","s":23},{"p":"902.8","s":18},{"p":"902.9","s":20},{"p":"903","s":23},{"p":"903.1","s":26},{"p":"903.2","s":20},{"p":"903.3","s":24},{"p":"903.4","s":19},{"p":"903.5","s":19},{"p":"903.6","s":23}],"bids":[{"p":"873.7","s":84},{"p":"872.2","s":29},{"p":"872.1","s":39},{"p":"872","s":29},{"p":"871.9","s":49},{"p":"871.8","s":29},{"p":"871.7","s":46},{"p":"871.6","s":46},{"p":"871.5","s":50},{"p":"871.4","s":41},{"p":"871.3","s":47},{"p":"871.2","s":46},{"p":"871.1","s":40},{"p":"871","s":40},{"p":"870.9","s":46},{"p":"870.8","s":40},{"p":"870.7","s":41},{"p":"870.6","s":29},{"p":"870.5","s":35},{"p":"870.4","s":32},{"p":"870.3","s":33},{"p":"870.2","s":38},{"p":"870.1","s":29},{"p":"870","s":34},{"p":"869.9","s":30},{"p":"869.8","s":37},{"p":"868.8","s":1},{"p":"860.5","s":1},{"p":"857.5","s":529},{"p":"857.3","s":26},{"p":"857.2","s":27},{"p":"857.1","s":27},{"p":"857","s":25},{"p":"856.9","s":22},{"p":"856.8","s":24},{"p":"856.7","s":27},{"p":"856.6","s":27},{"p":"856.5","s":21},{"p":"856.4","s":22},{"p":"856.3","s":27},{"p":"856.2","s":22},{"p":"856.1","s":23},{"p":"856","s":25},{"p":"855.9","s":20},{"p":"855.8","s":22},{"p":"855.7","s":21},{"p":"855.6","s":26},{"p":"855.5","s":20},{"p":"855.4","s":25},{"p":"855.3","s":24}],"contract":"CAT_USDT","exchange":"gateio","selection":"lowest_positive_trade_size","sha256":"5fe44ae9e332da2ab14d3135a51205a2337b2526f9b28b3289585e32eda7d7ba"}}}
